filehelper/__init__.py
filehelper/filehelpers.py
filehelper/filenaming.py
filehelper/filetaskmanager.py
filehelper-1.0.1.dist-info/LICENSE
filehelper-1.0.1.dist-info/METADATA
filehelper-1.0.1.dist-info/WHEEL
filehelper-1.0.1.dist-info/top_level.txt
filehelper-1.0.1.dist-info/RECORD
