Metadata-Version: 2.1
Name: filehelper
Version: 1.0.1
Summary: Helper functions to manage files
Home-page: https://github.com/tyrannican/filetools
Author: Jonathan Grizou, Graham Keenan
Author-email: jonathan.grizou@gmail.com, graham.keenan@outlook.com
License: MIT
Platform: UNKNOWN
Classifier: Programming Language :: Python :: 3
Classifier: License :: OSI Approved :: MIT License
Classifier: Operating System :: OS Independent
Requires-Python: >=3.6
